setup.py
bank_account_pizzani/Account.py
bank_account_pizzani/Client.py
bank_account_pizzani/Exporter.py
bank_account_pizzani/__init__.py
bank_account_pizzani.egg-info/PKG-INFO
bank_account_pizzani.egg-info/SOURCES.txt
bank_account_pizzani.egg-info/dependency_links.txt
bank_account_pizzani.egg-info/not-zip-safe
bank_account_pizzani.egg-info/top_level.txt