Metadata-Version: 1.0
Name: bank-account-pizzani
Version: 0.1
Summary: Bank Account
Home-page: UNKNOWN
Author: Bruno Pizzani Mendoza
Author-email: UNKNOWN
License: UNKNOWN
Platform: UNKNOWN
